TikTokLive/__init__.py
TikTokLive/__version__.py
TikTokLive/client/__init__.py
TikTokLive/client/client.py
TikTokLive/client/errors.py
TikTokLive/client/logger.py
TikTokLive/client/web/__init__.py
TikTokLive/client/web/web_base.py
TikTokLive/client/web/web_client.py
TikTokLive/client/web/web_presets.py
TikTokLive/client/web/web_settings.py
TikTokLive/client/web/web_signer.py
TikTokLive/client/web/web_utils.py
TikTokLive/client/web/routes/__init__.py
TikTokLive/client/web/routes/fetch_gift_list.py
TikTokLive/client/web/routes/fetch_image_data.py
TikTokLive/client/web/routes/fetch_is_live.py
TikTokLive/client/web/routes/fetch_room_id_api.py
TikTokLive/client/web/routes/fetch_room_id_live_html.py
TikTokLive/client/web/routes/fetch_room_info.py
TikTokLive/client/web/routes/fetch_signed_websocket.py
TikTokLive/client/web/routes/fetch_user_unique_id.py
TikTokLive/client/web/routes/fetch_video_data.py
TikTokLive/client/web/routes/send_room_chat.py
TikTokLive/client/web/routes/send_room_gift.py
TikTokLive/client/web/routes/send_room_like.py
TikTokLive/client/ws/__init__.py
TikTokLive/client/ws/ws_client.py
TikTokLive/client/ws/ws_connect.py
TikTokLive/client/ws/ws_utils.py
TikTokLive/events/__init__.py
TikTokLive/events/base_event.py
TikTokLive/events/custom_events.py
TikTokLive/events/proto_events.py
TikTokLive/proto/__init__.py
TikTokLive/proto/custom_extras.py
TikTokLive/proto/custom_proto.py
TikTokLive/proto/proto_utils.py
TikTokLive/proto/tiktok_proto.py
tiktoklive_fix-6.5.4.dist-info/licenses/LICENSE
tiktoklive_fix-6.5.4.dist-info/METADATA
tiktoklive_fix-6.5.4.dist-info/WHEEL
tiktoklive_fix-6.5.4.dist-info/top_level.txt
tiktoklive_fix-6.5.4.dist-info/RECORD
